.travis.yml
LICENSE.txt
MANIFEST.in
README.rst
requirements.txt
setup.py
Sixpack_client.egg-info/PKG-INFO
Sixpack_client.egg-info/SOURCES.txt
Sixpack_client.egg-info/dependency_links.txt
Sixpack_client.egg-info/requires.txt
Sixpack_client.egg-info/top_level.txt
sixpack/__init__.py
sixpack/sixpack.py
sixpack/test/__init__.py
sixpack/test/test_sixpack_client.py