Metadata-Version: 1.1
Name: Sixpack-client
Version: 1.2.0
Summary: Python client for Sixpack, an A/B testing framework under active development at SeatGeek
Home-page: http://github.com/seatgeek/sixpack-py
Author: SeatGeek
Author-email: hi@seatgeek.com
License: Copyright (c) 2013, SeatGeek, Inc.
